<?xml version="1.0" encoding="UTF-8"?><record_update table="question_choice">
    <question_choice action="INSERT_OR_UPDATE">
        <inactive>false</inactive>
        <order>200</order>
        <published_ref/>
        <question display_value="What is the size of this issue?">d9e7ba82833c72105d6894b6feaad31c</question>
        <sys_class_name>question_choice</sys_class_name>
        <sys_created_by>admin</sys_created_by>
        <sys_created_on>2025-10-26 18:24:40</sys_created_on>
        <sys_id>6c19b206833c72105d6894b6feaad37c</sys_id>
        <sys_mod_count>0</sys_mod_count>
        <sys_name>Medium</sys_name>
        <sys_package display_value="Safety" source="x_1604622_safety">6403a946837472105d6894b6feaad3dd</sys_package>
        <sys_policy/>
        <sys_scope display_value="Safety">6403a946837472105d6894b6feaad3dd</sys_scope>
        <sys_update_name>question_choice_6c19b206833c72105d6894b6feaad37c</sys_update_name>
        <sys_updated_by>admin</sys_updated_by>
        <sys_updated_on>2025-10-26 18:24:40</sys_updated_on>
        <text>Medium</text>
        <value>medium</value>
    </question_choice>
    <fx_price action="delete_multiple" query="id=6c19b206833c72105d6894b6feaad37c"/>
</record_update>
